digdata/checkpoint/__init__.py
digdata/checkpoint/operators.py
digdata-0.1.4.dist-info/METADATA
digdata-0.1.4.dist-info/WHEEL
digdata-0.1.4.dist-info/RECORD
